tdt4160/__init__.py
tdt4160/assembly.py
tdt4160/ijvm.py
tdt4160/uninitialized.py
tdt4160-1.1.3.dist-info/LICENSE
tdt4160-1.1.3.dist-info/METADATA
tdt4160-1.1.3.dist-info/WHEEL
tdt4160-1.1.3.dist-info/top_level.txt
tdt4160-1.1.3.dist-info/RECORD
