Metadata-Version: 2.1
Name: tdt4160
Version: 1.1.3
Summary: Easy simulations for lower level tasks
Home-page: https://gitgud.io/fish/tdt4160
Author: Fisherman's Friend
Author-email: fish@waifu.club
License: UNKNOWN
Platform: UNKNOWN
Classifier: Programming Language :: Python :: 3
Classifier: License :: OSI Approved :: GNU Affero General Public License v3 or later (AGPLv3+)
Classifier: Operating System :: OS Independent
Requires-Python: >=3.7
